hrfunc/__init__.py
hrfunc/hrfunc.py
hrfunc/hrhash.py
hrfunc/hrtree.py
hrfunc/observer.py
hrfunc-1.1.1.dist-info/licenses/LICENSE
hrfunc-1.1.1.dist-info/METADATA
hrfunc-1.1.1.dist-info/WHEEL
hrfunc-1.1.1.dist-info/top_level.txt
hrfunc-1.1.1.dist-info/RECORD
