Metadata-Version: 2.4
Name: hrfunc
Version: 1.1.1
Summary: Tools for modeling HRFs and estimating neural activity from fNIRS brain signals
Author-email: Denny Schaedig <dennys@wustl.edu>
License-Expression: BSD-3-Clause
Project-URL: Homepage, https://github.com/dennys246/hrfunc
Project-URL: Documentation, https://www.hrfunc.org
Classifier: Programming Language :: Python :: 3
Classifier: Operating System :: OS Independent
Requires-Python: >=3.8
License-File: LICENSE
Requires-Dist: numpy
Requires-Dist: mne
Requires-Dist: mne_nirs
Requires-Dist: scipy
Requires-Dist: nilearn
Requires-Dist: matplotlib
Dynamic: license-file
